[
  {
    "tableaumetrics": {
      "keyWord": "Competitor 1 Details",
      "reportUrl": "https://tableau.internal.deloitte.com/views/AnthemLODashboard/Home?:embed=y&:showShareOptions=true&:display_count=no&:showVizHome=no",
      "sheetName": "Incidents Home4",
      "columnName": [
        "SUM([Open At Beginning])",
        "SUM([New Created])"
      ],
      "columnValue": [
        "Open At Beginning",
        "New Created"
      ]
    }
  },
  {
    "tableaumetrics": {
      "keyWord": "Incidents 4 Details",
      "reportUrl": "https://tableau.internal.deloitte.com/views/AnthemLODashboard/Home?:embed=y&:showShareOptions=true&:display_count=no&:showVizHome=no",
      "sheetName": "Incidents Home4",
      "columnName": [
        "Measure Names",
        "Measure Values",
		"Prior Complex ChangeType"
      ],
      "columnValue": [
        "Open At Beginning",
        "New Created"
      ]
    }
  }
]